[{
    "type": "cam_centerred1",
    "blocktextname": "is_center_red_line",
    "message0": "%{BKY_IS_CENTER_RED_LINE}",
    "output": null,
    "colour": 0
}, {
    "type": "cam_centerred2",
    "blocktextname": "is_center_red_line",
    "message0": "%{BKY_IS_CENTER_RED_LINE} %1",
    "args0": [{
        "type": "input_value",
        "name": "CAM",
        "check": null
    }],
    "output": null,
    "colour": 0
}, {
    "type": "cam_leftred1",
    "blocktextname": "is_left_red_line",
    "message0": "%{BKY_IS_LEFT_RED_LINE}",
    "output": null,
    "colour": 0
}, {
    "type": "cam_leftred2",
    "blocktextname": "is_left_red_line",
    "message0": "%{BKY_IS_LEFT_RED_LINE} %1",
    "args0": [{
        "type": "input_value",
        "name": "CAM",
        "check": null
    }],
    "output": null,
    "colour": 0
}, {
    "type": "cam_rightred1",
    "blocktextname": "is_right_red_line",
    "message0": "%{BKY_IS_RIGHT_RED_LINE}",
    "output": null,
    "colour": 0
}, {
    "type": "cam_rightred2",
    "blocktextname": "is_right_red_line",
    "message0": "%{BKY_IS_RIGHT_RED_LINE} %1",
    "args0": [{
        "type": "input_value",
        "name": "CAM",
        "check": null
    }],
    "output": null,
    "colour": 0
}, {
    "type": "cam_isred1",
    "blocktextname": "is_there_red_line",
    "message0": "%{BKY_IS_THERE_RED_LINE}",
    "output": null,
    "colour": 0
}, {
    "type": "cam_isred2",
    "blocktextname": "is_there_red_line",
    "message0": "%{BKY_IS_THERE_RED_LINE} %1",
    "args0": [{
        "type": "input_value",
        "name": "CAM",
        "check": null
    }],
    "output": null,
    "colour": 0
}, {
    "type": "cam_centerblack1",
    "blocktextname": "is_center_black_line",
    "message0": "%{BKY_IS_CENTER_BLACK_LINE}",
    "output": null,
    "colour": 0
}, {
    "type": "cam_centerblack2",
    "blocktextname": "is_center_black_line",
    "message0": "%{BKY_IS_CENTER_BLACK_LINE} %1",
    "args0": [{
        "type": "input_value",
        "name": "CAM",
        "check": null
    }],
    "output": null,
    "colour": 0
}, {
    "type": "cam_leftblack1",
    "blocktextname": "is_left_black_line",
    "message0": "%{BKY_IS_LEFT_BLACK_LINE}",
    "output": null,
    "colour": 0
}, {
    "type": "cam_leftblack2",
    "blocktextname": "is_left_black_line",
    "message0": "%{BKY_IS_LEFT_BLACK_LINE} %1",
    "args0": [{
        "type": "input_value",
        "name": "CAM",
        "check": null
    }],
    "output": null,
    "colour": 0
}, {
    "type": "cam_rightblack1",
    "blocktextname": "is_right_black_line",
    "message0": "%{BKY_IS_RIGHT_BLACK_LINE}",
    "output": null,
    "colour": 0
}, {
    "type": "cam_rightblack2",
    "blocktextname": "is_right_black_line",
    "message0": "%{BKY_IS_RIGHT_BLACK_LINE} %1",
    "args0": [{
        "type": "input_value",
        "name": "CAM",
        "check": null
    }],
    "output": null,
    "colour": 0
}, {
    "type": "cam_isblack1",
    "blocktextname": "is_there_black_line",
    "message0": "%{BKY_IS_THERE_BLACK_LINE}",
    "output": null,
    "colour": 0
}, {
    "type": "cam_isblack2",
    "blocktextname": "is_there_black_line",
    "message0": "%{BKY_IS_THERE_BLACK_LINE} %1",
    "args0": [{
        "type": "input_value",
        "name": "CAM",
        "check": null
    }],
    "output": null,
    "colour": 0
}, {
    "type": "cam_centerblue1",
    "blocktextname": "is_center_blue_line",
    "message0": "%{BKY_IS_CENTER_BLUE_LINE}",
    "output": null,
    "colour": 0
}, {
    "type": "cam_centerblue2",
    "blocktextname": "is_center_blue_line",
    "message0": "%{BKY_IS_CENTER_BLUE_LINE} %1",
    "args0": [{
        "type": "input_value",
        "name": "CAM",
        "check": null
    }],
    "output": null,
    "colour": 0
}, {
    "type": "cam_leftblue1",
    "blocktextname": "is_left_blue_line",
    "message0": "%{BKY_IS_LEFT_BLUE_LINE}",
    "output": null,
    "colour": 0
}, {
    "type": "cam_leftblue2",
    "blocktextname": "is_left_blue_line",
    "message0": "%{BKY_IS_LEFT_BLUE_LINE} %1",
    "args0": [{
        "type": "input_value",
        "name": "CAM",
        "check": null
    }],
    "output": null,
    "colour": 0
}, {
    "type": "cam_rightblue1",
    "blocktextname": "is_right_blue_line",
    "message0": "%{BKY_IS_RIGHT_BLUE_LINE}",
    "output": null,
    "colour": 0
}, {
    "type": "cam_rightblue2",
    "blocktextname": "is_right_blue_line",
    "message0": "%{BKY_IS_RIGHT_BLUE_LINE} %1",
    "args0": [{
        "type": "input_value",
        "name": "CAM",
        "check": null
    }],
    "output": null,
    "colour": 0
}, {
    "type": "cam_isblue1",
    "blocktextname": "is_there_blue_line",
    "message0": "%{BKY_IS_THERE_BLUE_LINE}",
    "output": null,
    "colour": 0
}, {
    "type": "cam_isblue2",
    "blocktextname": "is_there_blue_line",
    "message0": "%{BKY_IS_THERE_BLUE_LINE} %1",
    "args0": [{
        "type": "input_value",
        "name": "CAM",
        "check": null
    }],
    "output": null,
    "colour": 0
}, {
    "type": "cam_faceleft1",
    "blocktextname": "is_left_face",
    "message0": "%{BKY_IS_LEFT_FACE}",
    "output": null,
    "colour": 0
}, {
    "type": "cam_faceleft2",
    "blocktextname": "is_left_face",
    "message0": "%{BKY_IS_LEFT_FACE} %1",
    "args0": [{
        "type": "input_value",
        "name": "CAM",
        "check": null
    }],
    "output": null,
    "colour": 0
}, {
    "type": "cam_faceright1",
    "blocktextname": "is_right_face",
    "message0": "%{BKY_IS_RIGHT_FACE}",
    "output": null,
    "colour": 0
}, {
    "type": "cam_faceright2",
    "blocktextname": "is_right_face",
    "message0": "%{BKY_IS_RIGHT_FACE} %1",
    "args0": [{
        "type": "input_value",
        "name": "CAM",
        "check": null
    }],
    "output": null,
    "colour": 0
}, {
    "type": "cam_faceup1",
    "blocktextname": "is_up_face",
    "message0": "%{BKY_IS_UP_FACE}",
    "output": null,
    "colour": 0
}, {
    "type": "cam_faceup2",
    "blocktextname": "is_up_face",
    "message0": "%{BKY_IS_UP_FACE} %1",
    "args0": [{
        "type": "input_value",
        "name": "CAM",
        "check": null
    }],
    "output": null,
    "colour": 0
}, {
    "type": "cam_facedown1",
    "blocktextname": "is_down_face",
    "message0": "%{BKY_IS_DOWN_FACE}",
    "output": null,
    "colour": 0
}, {
    "type": "cam_facedown2",
    "blocktextname": "is_down_face",
    "message0": "%{BKY_IS_DOWN_FACE} %1",
    "args0": [{
        "type": "input_value",
        "name": "CAM",
        "check": null
    }],
    "output": null,
    "colour": 0
}, {
    "type": "cam_facecenter1",
    "blocktextname": "is_center_face",
    "message0": "%{BKY_IS_CENTER_FACE}",
    "output": null,
    "colour": 0
}, {
    "type": "cam_facecenter2",
    "blocktextname": "is_center_face",
    "message0": "%{BKY_IS_CENTER_FACE} %1",
    "args0": [{
        "type": "input_value",
        "name": "CAM",
        "check": null
    }],
    "output": null,
    "colour": 0
}, {
    "type": "cam_isface1",
    "blocktextname": "is_there_face",
    "message0": "%{BKY_IS_THERE_FACE}",
    "output": null,
    "colour": 0
}, {
    "type": "cam_isface2",
    "blocktextname": "is_there_face",
    "message0": "%{BKY_IS_THERE_FACE} %1",
    "args0": [{
        "type": "input_value",
        "name": "CAM",
        "check": null
    }],
    "output": null,
    "colour": 0
}, {
    "type": "cam_linecross1",
    "blocktextname": "is_line_crossing",
    "message0": "%{BKY_IS_LINE_CROSSING}",
    "output": null,
    "colour": 0
}, {
    "type": "cam_linecross2",
    "blocktextname": "is_line_crossing",
    "message0": "%{BKY_IS_LINE_CROSSING} %1",
    "args0": [{
        "type": "input_value",
        "name": "CAM",
        "check": null
    }],
    "output": null,
    "colour": 0
}, {
    "type": "cam_facehappy1",
    "blocktextname": "is_any_face_happy",
    "message0": "%{BKY_IS_ANY_FACE_HAPPY}",
    "output": null,
    "colour": 0
}, {
    "type": "cam_facehappy2",
    "blocktextname": "is_any_face_happy",
    "message0": "%{BKY_IS_ANY_FACE_HAPPY} %1",
    "args0": [{
        "type": "input_value",
        "name": "CAM",
        "check": null
    }],
    "output": null,
    "colour": 0
}, {
    "type": "cam_faceangry1",
    "blocktextname": "is_any_face_angry",
    "message0": "%{BKY_IS_ANY_FACE_ANGRY}",
    "output": null,
    "colour": 0
}, {
    "type": "cam_faceangry2",
    "blocktextname": "is_any_face_angry",
    "message0": "%{BKY_IS_ANY_FACE_ANGRY} %1",
    "args0": [{
        "type": "input_value",
        "name": "CAM",
        "check": null
    }],
    "output": null,
    "colour": 0
}, {
    "type": "cam_faceneutral1",
    "blocktextname": "is_any_face_neutral",
    "message0": "%{BKY_IS_ANY_FACE_NEUTRAL}",
    "output": null,
    "colour": 0
}, {
    "type": "cam_faceneutral2",
    "blocktextname": "is_any_face_neutral",
    "message0": "%{BKY_IS_ANY_FACE_NEUTRAL} %1",
    "args0": [{
        "type": "input_value",
        "name": "CAM",
        "check": null
    }],
    "output": null,
    "colour": 0
}, {
    "type": "cam_facesad1",
    "blocktextname": "is_any_face_sad",
    "message0": "%{BKY_IS_ANY_FACE_SAD}",
    "output": null,
    "colour": 0
}, {
    "type": "cam_facesad2",
    "blocktextname": "is_any_face_sad",
    "message0": "%{BKY_IS_ANY_FACE_SAD} %1",
    "args0": [{
        "type": "input_value",
        "name": "CAM",
        "check": null
    }],
    "output": null,
    "colour": 0
}, {
    "type": "cam_facesurprised1",
    "blocktextname": "is_any_face_surprised",
    "message0": "%{BKY_IS_ANY_FACE_SURPRISED}",
    "output": null,
    "colour": 0
}, {
    "type": "cam_facesurprised2",
    "blocktextname": "is_any_face_surprised",
    "message0": "%{BKY_IS_ANY_FACE_SURPRISED} %1",
    "args0": [{
        "type": "input_value",
        "name": "CAM",
        "check": null
    }],
    "output": null,
    "colour": 0
}, {
    "type": "cam_istag1",
    "blocktextname": "is_tag",
    "message0": "%{BKY_IS_TAG}",
    "args0": [{
        "type": "field_number",
        "name": "NUM",
        "value": 0
    }],
    "output": null,
    "colour": 0
}, {
    "type": "cam_istag2",
    "blocktextname": "is_tag",
    "message0": "%{BKY_IS_TAG} %2",
    "args0": [{
        "type": "field_number",
        "name": "NUM",
        "value": 0
    }, {
        "type": "input_value",
        "name": "CAM",
        "check": null
    }],
    "output": null,
    "colour": 0
}, {
    "type": "cam_isanytag1",
    "blocktextname": "is_any_tag",
    "message0": "%{BKY_IS_ANY_TAG}",
    "output": null,
    "colour": 0
}, {
    "type": "cam_isanytag2",
    "blocktextname": "is_any_tag",
    "message0": "%{BKY_IS_ANY_TAG} %1",
    "args0": [{
        "type": "input_value",
        "name": "CAM",
        "check": null
    }],
    "output": null,
    "colour": 0
}, {
    "type": "cam_tagleft1",
    "blocktextname": "tag_on_the_left",
    "message0": "%{BKY_TAG_ON_THE_LEFT}",
    "output": null,
    "colour": 0
}, {
    "type": "cam_tagleft2",
    "blocktextname": "tag_on_the_left",
    "message0": "%{BKY_TAG_ON_THE_LEFT} %1",
    "args0": [{
        "type": "input_value",
        "name": "CAM",
        "check": null
    }],
    "output": null,
    "colour": 0
}, {
    "type": "cam_tagright1",
    "blocktextname": "tag_on_the_right",
    "message0": "%{BKY_TAG_ON_THE_RIGHT}",
    "output": null,
    "colour": 0
}, {
    "type": "cam_tagright2",
    "blocktextname": "tag_on_the_right",
    "message0": "%{BKY_TAG_ON_THE_RIGHT} %1",
    "args0": [{
        "type": "input_value",
        "name": "CAM",
        "check": null
    }],
    "output": null,
    "colour": 0
}, {
    "type": "cam_tagcenter1",
    "blocktextname": "tag_on_the_center",
    "message0": "%{BKY_TAG_ON_THE_CENTER}",
    "args0": [{
        "type": "field_number",
        "name": "NUM",
        "value": 0
    }],
    "output": null,
    "colour": 0
}, {
    "type": "cam_tagcenter2",
    "blocktextname": "tag_on_the_center",
    "message0": "%{BKY_TAG_ON_THE_CENTER} %2",
    "args0": [{
        "type": "field_number",
        "name": "NUM",
        "value": 0
    }, {
        "type": "input_value",
        "name": "CAM",
        "check": null
    }],
    "output": null,
    "colour": 0
}, {
    "type": "cam_image1",
    "blocktextname": "is_image",
    "message0": "%{BKY_IS_IMAGE}",
    "args0": [{
        "type": "field_input",
        "name": "TEXT",
        "text": "img"
    }],
    "output": null,
    "colour": 0
}, {
    "type": "cam_image2",
    "blocktextname": "is_image",
    "message0": "%{BKY_IS_IMAGE} %2",
    "args0": [{
        "type": "field_input",
        "name": "TEXT",
        "text": "img"
    }, {
        "type": "input_value",
        "name": "CAM",
        "check": null
    }],
    "output": null,
    "colour": 0
}]
